recoflow/__init__.py
recoflow/datasets.py
recoflow/metrics.py
recoflow/models.py
recoflow/preprocessing.py
recoflow/recommend.py
recoflow/utils.py
recoflow/vis.py
recoflow-0.0.7.dist-info/LICENSE
recoflow-0.0.7.dist-info/WHEEL
recoflow-0.0.7.dist-info/METADATA
recoflow-0.0.7.dist-info/RECORD
